GeeksforgeeksMicroprocessorLectureNotes/README.md
GeeksforgeeksMicroprocessorLectureNotes/__init__.py
GeeksforgeeksMicroprocessorLectureNotes/__main__.py
GeeksforgeeksMicroprocessorLectureNotes/file.epub
GeeksforgeeksMicroprocessorLectureNotes/index.html
GeeksforgeeksMicroprocessorLectureNotes/css/__init__.py
GeeksforgeeksMicroprocessorLectureNotes/css/annotations.css
GeeksforgeeksMicroprocessorLectureNotes/css/main.css
GeeksforgeeksMicroprocessorLectureNotes/css/normalize.css
GeeksforgeeksMicroprocessorLectureNotes/css/popup.css
GeeksforgeeksMicroprocessorLectureNotes/font/__init__.py
GeeksforgeeksMicroprocessorLectureNotes/font/fontello.eot
GeeksforgeeksMicroprocessorLectureNotes/font/fontello.svg
GeeksforgeeksMicroprocessorLectureNotes/font/fontello.ttf
GeeksforgeeksMicroprocessorLectureNotes/font/fontello.woff
GeeksforgeeksMicroprocessorLectureNotes/img/__init__.py
GeeksforgeeksMicroprocessorLectureNotes/img/annotator-glyph-sprite.png
GeeksforgeeksMicroprocessorLectureNotes/img/annotator-icon-sprite.png
GeeksforgeeksMicroprocessorLectureNotes/img/apple-touch-icon.png
GeeksforgeeksMicroprocessorLectureNotes/img/cancelfullscreen.png
GeeksforgeeksMicroprocessorLectureNotes/img/close.png
GeeksforgeeksMicroprocessorLectureNotes/img/fullscreen.png
GeeksforgeeksMicroprocessorLectureNotes/img/loader.gif
GeeksforgeeksMicroprocessorLectureNotes/img/menu-icon.png
GeeksforgeeksMicroprocessorLectureNotes/img/save.png
GeeksforgeeksMicroprocessorLectureNotes/img/saved.png
GeeksforgeeksMicroprocessorLectureNotes/img/settings-s.png
GeeksforgeeksMicroprocessorLectureNotes/img/settings.png
GeeksforgeeksMicroprocessorLectureNotes/img/star.png
GeeksforgeeksMicroprocessorLectureNotes/js/__init__.py
GeeksforgeeksMicroprocessorLectureNotes/js/epub.js
GeeksforgeeksMicroprocessorLectureNotes/js/epub.min.js
GeeksforgeeksMicroprocessorLectureNotes/js/epub.min.map
GeeksforgeeksMicroprocessorLectureNotes/js/hooks.min.js
GeeksforgeeksMicroprocessorLectureNotes/js/hooks.min.map
geeksforgeeks_microprocessor_lecture_notes-2024.3.3.0.dist-info/METADATA
geeksforgeeks_microprocessor_lecture_notes-2024.3.3.0.dist-info/WHEEL
geeksforgeeks_microprocessor_lecture_notes-2024.3.3.0.dist-info/entry_points.txt
geeksforgeeks_microprocessor_lecture_notes-2024.3.3.0.dist-info/top_level.txt
geeksforgeeks_microprocessor_lecture_notes-2024.3.3.0.dist-info/RECORD
